{
    "_cit_tax_rate": {
        "long_name": " ",
        "description": " ",
        "itr_ref": " ",
        "notes": "",
        "row_var": "Year",
        "row_label": [
            "2022"
        ],
        "start_year": 2022,
        "cpi_inflatable": false,
        "cpi_inflated": false,
        "col_var": "Value",
        "col_label": ["Value"],
        "boolean_value": false,
        "integer_value": false,
        "value": [0.18],
        "range": {
            "min": 0.0,
            "max": 1.0
        },
        "out_of_range_minmsg": "",
        "out_of_range_maxmsg": "",
        "out_of_range_action": "stop"
    },
    "_depr_prop_rate": {
        "long_name": " ",
        "description": " ",
        "itr_ref": " ",
        "notes": "",
        "row_var": "Year",
        "row_label": [
            "2022"
        ],
        "start_year": 2022,
        "cpi_inflatable": false,
        "cpi_inflated": false,
        "col_var": "Value",
        "col_label": ["Value"],
        "boolean_value": false,
        "integer_value": false,
        "value": [0.17],
        "range": {
            "min": 0.0,
            "max": 1.0
        },
        "out_of_range_minmsg": "",
        "out_of_range_maxmsg": "",
        "out_of_range_action": "stop"
    },
    "_depr_int_rate": {
        "long_name": " ",
        "description": " ",
        "itr_ref": " ",
        "notes": "",
        "row_var": "Year",
        "row_label": [
            "2022"
        ],
        "start_year": 2022,
        "cpi_inflatable": false,
        "cpi_inflated": false,
        "col_var": "Value",
        "col_label": ["Value"],
        "boolean_value": false,
        "integer_value": false,
        "value": [0.24],
        "range": {
            "min": 0.0,
            "max": 1.0
        },
        "out_of_range_minmsg": "",
        "out_of_range_maxmsg": "",
        "out_of_range_action": "stop"
    },
    "_depr_rate_assets_NPO": {
        "long_name": " ",
        "description": " ",
        "itr_ref": " ",
        "notes": "",
        "row_var": "Year",
        "row_label": [
            "2022"
        ],
        "start_year": 2022,
        "cpi_inflatable": false,
        "cpi_inflated": false,
        "col_var": "Value",
        "col_label": ["Value"],
        "boolean_value": false,
        "integer_value": false,
        "value": [1],
        "range": {
            "min": 0,
            "max": 1
        },
        "out_of_range_minmsg": "",
        "out_of_range_maxmsg": "",
        "out_of_range_action": "stop"
    },
    "_ded_disable_rate": {
        "long_name": " ",
        "description": " ",
        "itr_ref": " ",
        "notes": "",
        "row_var": "Year",
        "row_label": [
            "2022"
        ],
        "start_year": 2022,
        "cpi_inflatable": false,
        "cpi_inflated": false,
        "col_var": "Value",
        "col_label": ["Value"],
        "boolean_value": false,
        "integer_value": false,
        "value": [1.5],
        "range": {
            "min": 0,
            "max": 100
        },
        "out_of_range_minmsg": "",
        "out_of_range_maxmsg": "",
        "out_of_range_action": "stop"
    },
    "_rate_ded_total_licensing": {
        "long_name": " ",
        "description": " ",
        "itr_ref": " ",
        "notes": "",
        "row_var": "Year",
        "row_label": [
            "2022"
        ],
        "start_year": 2022,
        "cpi_inflatable": false,
        "cpi_inflated": false,
        "col_var": "Value",
        "col_label": ["Value"],
        "boolean_value": false,
        "integer_value": false,
        "value": [1],
        "range": {
            "min": 0,
            "max": 1
        },
        "out_of_range_minmsg": "",
        "out_of_range_maxmsg": "",
        "out_of_range_action": "stop"
    },
    "_rate_ded_total_joint_act": {
        "long_name": " ",
        "description": " ",
        "itr_ref": " ",
        "notes": "",
        "row_var": "Year",
        "row_label": [
            "2022"
        ],
        "start_year": 2022,
        "cpi_inflatable": false,
        "cpi_inflated": false,
        "col_var": "Value",
        "col_label": ["Value"],
        "boolean_value": false,
        "integer_value": false,
        "value": [1],
        "range": {
            "min": 0,
            "max": 1
        },
        "out_of_range_minmsg": "",
        "out_of_range_maxmsg": "",
        "out_of_range_action": "stop"
    },
    "_rate_ded_tot_org_prod_border": {
        "long_name": " ",
        "description": " ",
        "itr_ref": " ",
        "notes": "",
        "row_var": "Year",
        "row_label": [
            "2022"
        ],
        "start_year": 2022,
        "cpi_inflatable": false,
        "cpi_inflated": false,
        "col_var": "Value",
        "col_label": ["Value"],
        "boolean_value": false,
        "integer_value": false,
        "value": [1],
        "range": {
            "min": 0,
            "max": 1
        },
        "out_of_range_minmsg": "",
        "out_of_range_maxmsg": "",
        "out_of_range_action": "stop"
    },
    "_rate_exempt_patent": {
        "long_name": " ",
        "description": " ",
        "itr_ref": " ",
        "notes": "",
        "row_var": "Year",
        "row_label": [
            "2022"
        ],
        "start_year": 2022,
        "cpi_inflatable": false,
        "cpi_inflated": false,
        "col_var": "Value",
        "col_label": ["Value"],
        "boolean_value": false,
        "integer_value": false,
        "value": [1],
        "range": {
            "min": 0,
            "max": 1
        },
        "out_of_range_minmsg": "",
        "out_of_range_maxmsg": "",
        "out_of_range_action": "stop"
    },
    "_rate_exempt_approved_act": {
        "long_name": " ",
        "description": " ",
        "itr_ref": " ",
        "notes": "",
        "row_var": "Year",
        "row_label": [
            "2022"
        ],
        "start_year": 2022,
        "cpi_inflatable": false,
        "cpi_inflated": false,
        "col_var": "Value",
        "col_label": ["Value"],
        "boolean_value": false,
        "integer_value": false,
        "value": [1],
        "range": {
            "min": 0,
            "max": 1
        },
        "out_of_range_minmsg": "",
        "out_of_range_maxmsg": "",
        "out_of_range_action": "stop"
    },
    "_rate_tax_exemption": {
        "long_name": " ",
        "description": " ",
        "itr_ref": " ",
        "notes": "",
        "row_var": "Year",
        "row_label": [
            "2022"
        ],
        "start_year": 2022,
        "cpi_inflatable": false,
        "cpi_inflated": false,
        "col_var": "Value",
        "col_label": ["Value"],
        "boolean_value": false,
        "integer_value": false,
        "value": [1],
        "range": {
            "min": 0,
            "max": 1
        },
        "out_of_range_minmsg": "",
        "out_of_range_maxmsg": "",
        "out_of_range_action": "stop"
    },
      "_loss_cf_limit": {
          "long_name": " ",
          "description": " ",
          "itr_ref": " ",
          "notes": "",
          "row_var": "Year",
          "row_label": [
              "2022"
          ],
          "start_year": 2022,
          "cpi_inflatable": false,
          "cpi_inflated": false,
          "col_var": "Value",
          "col_label": ["Value"],
          "boolean_value": false,
          "integer_value": false,
          "value": [5],
          "range": {
              "min": 0,
              "max": 10
          },
          "out_of_range_minmsg": "",
          "out_of_range_maxmsg": "",
          "out_of_range_action": "stop"
      },
    "_rate_tc_app_projects": {
        "long_name": " ",
        "description": " ",
        "itr_ref": " ",
        "notes": "",
        "row_var": "Year",
        "row_label": [
            "2022"
        ],
        "start_year": 2022,
        "cpi_inflatable": false,
        "cpi_inflated": false,
        "col_var": "Value",
        "col_label": ["Value"],
        "boolean_value": false,
        "integer_value": false,
        "value": [1],
        "range": {
            "min": 0,
            "max": 1
        },
        "out_of_range_minmsg": "",
        "out_of_range_maxmsg": "",
        "out_of_range_action": "stop"
    },
    "_rate_tc_free_supply": {
        "long_name": " ",
        "description": " ",
        "itr_ref": " ",
        "notes": "",
        "row_var": "Year",
        "row_label": [
            "2022"
        ],
        "start_year": 2022,
        "cpi_inflatable": false,
        "cpi_inflated": false,
        "col_var": "Value",
        "col_label": ["Value"],
        "boolean_value": false,
        "integer_value": false,
        "value": [1],
        "range": {
            "min": 0,
            "max": 1
        },
        "out_of_range_minmsg": "",
        "out_of_range_maxmsg": "",
        "out_of_range_action": "stop"
    },
    
     "_rate_TO_tax_comm": {
        "long_name": "Turnover tax rate applicable to income from commercial (purchase and sale) activities",
        "description": "Turnover Tax ",
        "itr_ref": "Tax Law",
        "notes": "",
        "row_var": "Year",
        "row_label": [
            "2022"
        ],
        "start_year": 2022,
        "cpi_inflatable": false,
        "cpi_inflated": false,
        "col_var": "Value",
        "col_label": ["Value"],
        "boolean_value": false,
        "integer_value": false,
        "value": [0.05],
        "range": {
            "min": 0.0,
            "max": 1.0
        },
        "out_of_range_minmsg": "",
        "out_of_range_maxmsg": "",
        "out_of_range_action": "stop"
    },
     "_rate_mintax_comm": {
        "long_name": "Minimum tax rate applicable to income from commercial (purchase and sale) activities",
        "description": "Turnover Tax ",
        "itr_ref": "Tax Law",
        "notes": "",
        "row_var": "Year",
        "row_label": [
            "2022"
        ],
        "start_year": 2022,
        "cpi_inflatable": false,
        "cpi_inflated": false,
        "col_var": "Value",
        "col_label": ["Value"],
        "boolean_value": false,
        "integer_value": false,
        "value": [0.015],
        "range": {
            "min": 0.0,
            "max": 1.0
        },
        "out_of_range_minmsg": "",
        "out_of_range_maxmsg": "",
        "out_of_range_action": "stop"
    },
     "_rate_mintax_catering": {
        "long_name": "Minimum tax rate applicable to income from public catering",
        "description": "Turnover Tax ",
        "itr_ref": "Tax Law",
        "notes": "",
        "row_var": "Year",
        "row_label": [
            "2022"
        ],
        "start_year": 2022,
        "cpi_inflatable": false,
        "cpi_inflated": false,
        "col_var": "Value",
        "col_label": ["Value"],
        "boolean_value": false,
        "integer_value": false,
        "value": [0.015],
        "range": {
            "min": 0.0,
            "max": 1.0
        },
        "out_of_range_minmsg": "",
        "out_of_range_maxmsg": "",
        "out_of_range_action": "stop"
    },
    "_rate_exp_ded_comm": {
       "long_name": "Rate of deduction for cost of acquisition of goods related to income from commercial (purchase and sale) activities ",
       "description": "Turnover Tax ",
       "itr_ref": "Tax Law",
       "notes": "",
       "row_var": "Year",
       "row_label": [
           "2022"
       ],
       "start_year": 2022,
       "cpi_inflatable": false,
       "cpi_inflated": false,
       "col_var": "Value",
       "col_label": ["Value"],
       "boolean_value": false,
       "integer_value": false,
       "value": [0.04],
       "range": {
           "min": 0.0,
           "max": 1.0
       },
       "out_of_range_minmsg": "",
       "out_of_range_maxmsg": "",
       "out_of_range_action": "stop"
   },
    "_rate_exp_ded_catering": {
       "long_name": "Rate of deduction for expenses related to income from public catering",
       "description": "Turnover Tax ",
       "itr_ref": "Tax Law",
       "notes": "",
       "row_var": "Year",
       "row_label": [
           "2022"
       ],
       "start_year": 2022,
       "cpi_inflatable": false,
       "cpi_inflated": false,
       "col_var": "Value",
       "col_label": ["Value"],
       "boolean_value": false,
       "integer_value": false,
       "value": [0.04],
       "range": {
           "min": 0.0,
           "max": 1.0
       },
       "out_of_range_minmsg": "",
       "out_of_range_maxmsg": "",
       "out_of_range_action": "stop"
   },
     "_rate_TO_tax_catering": {
        "long_name": "6.2. Tax rate on income from activities in the field of public catering",
        "description": "Turnover Tax ",
        "itr_ref": "Tax Law",
        "notes": "",
        "row_var": "Year",
        "row_label": [
            "2022"
        ],
        "start_year": 2022,
        "cpi_inflatable": false,
        "cpi_inflated": false,
        "col_var": "Value",
        "col_label": ["Value"],
        "boolean_value": false,
        "integer_value": false,
        "value": [0.06],
        "range": {
            "min": 0.0,
            "max": 1.0
        },
        "out_of_range_minmsg": "",
        "out_of_range_maxmsg": "",
        "out_of_range_action": "stop"
    },
    "_rate_TO_tax_trading": {
       "long_name": "Turnover Tax Rate applicable to Turnover from Trading of secondary raw materials",
       "description": "Turnover Tax Rate applicable to Turnover from Trading of secondary raw materials",
       "itr_ref": "Tax Law",
       "notes": "",
       "row_var": "Year",
       "row_label": [
           "2022"
       ],
       "start_year": 2022,
       "cpi_inflatable": false,
       "cpi_inflated": false,
       "col_var": "Value",
       "col_label": ["Value"],
       "boolean_value": false,
       "integer_value": false,
       "value": [0.015],
       "range": {
           "min": 0.0,
           "max": 1.0
       },
       "out_of_range_minmsg": "",
       "out_of_range_maxmsg": "",
       "out_of_range_action": "stop"
   },
     "_rate_TO_tax_newspaper": {
        "long_name": "Turnover Tax Rate applicable to Turnover from Sale of Newspaper",
        "description": "Turnover Tax ",
        "itr_ref": "Tax Law",
        "notes": "",
        "row_var": "Year",
        "row_label": [
            "2022"
        ],
        "start_year": 2022,
        "cpi_inflatable": false,
        "cpi_inflated": false,
        "col_var": "Value",
        "col_label": ["Value"],
        "boolean_value": false,
        "integer_value": false,
        "value": [0.015],
        "range": {
            "min": 0.0,
            "max": 1.0
        },
        "out_of_range_minmsg": "",
        "out_of_range_maxmsg": "",
        "out_of_range_action": "stop"
    },
     "_rate_TO_tax_production": {
        "long_name": "Turnover Tax Rate applicable to Turnover from production activities",
        "description": "Turnover Tax ",
        "itr_ref": "Tax Law",
        "notes": "",
        "row_var": "Year",
        "row_label": [
            "2022"
        ],
        "start_year": 2022,
        "cpi_inflatable": false,
        "cpi_inflated": false,
        "col_var": "Value",
        "col_label": ["Value"],
        "boolean_value": false,
        "integer_value": false,
        "value": [0.035],
        "range": {
            "min": 0.0,
            "max": 1.0
        },
        "out_of_range_minmsg": "",
        "out_of_range_maxmsg": "",
        "out_of_range_action": "stop"
    },
     "_rate_TO_tax_rent_royalty": {
        "long_name": "Turnover Tax Rate applicable to income from rent, royalty, disposal of real estate",
        "description": "Turnover Tax Rate applicable to income from rent, royalty, disposal of real estate",
        "itr_ref": "Tax Law",
        "notes": "",
        "row_var": "Year",
        "row_label": [
            "2022"
        ],
        "start_year": 2022,
        "cpi_inflatable": false,
        "cpi_inflated": false,
        "col_var": "Value",
        "col_label": ["Value"],
        "boolean_value": false,
        "integer_value": false,
        "value": [0.1],
        "range": {
            "min": 0.0,
            "max": 1.0
        },
        "out_of_range_minmsg": "",
        "out_of_range_maxmsg": "",
        "out_of_range_action": "stop"
    },
    "_rate_TO_tax_notary": {
       "long_name": "Tax Rate  4",
       "description": "Turnover Tax ",
       "itr_ref": "Tax Law",
       "notes": "",
       "row_var": "Year",
       "row_label": [
           "2022"
       ],
       "start_year": 2022,
       "cpi_inflatable": false,
       "cpi_inflated": false,
       "col_var": "Value",
       "col_label": ["Value"],
       "boolean_value": false,
       "integer_value": false,
       "value": [0.10],
       "range": {
           "min": 0.0,
           "max": 1.0
       },
       "out_of_range_minmsg": "",
       "out_of_range_maxmsg": "",
       "out_of_range_action": "stop"
   },
"_rate_TO_tax_lottery": {
    "long_name": "Tax Rate  5",
    "description": "Turnover Tax ",
    "itr_ref": "Tax Law",
    "notes": "",
    "row_var": "Year",
    "row_label": [
        "2022"
    ],
    "start_year": 2022,
    "cpi_inflatable": false,
    "cpi_inflated": false,
    "col_var": "Value",
    "col_label": ["Value"],
    "boolean_value": false,
    "integer_value": false,
    "value": [0.25],
    "range": {
        "min": 0.0,
        "max": 1.0
    },
    "out_of_range_minmsg": "",
    "out_of_range_maxmsg": "",
    "out_of_range_action": "stop"
},
"_rate_TO_tax_asset_catering": {
    "long_name": "Tax Rate  6",
    "description": "Turnover Tax ",
    "itr_ref": "Tax Law",
    "notes": "",
    "row_var": "Year",
    "row_label": [
        "2022"
    ],
    "start_year": 2022,
    "cpi_inflatable": false,
    "cpi_inflated": false,
    "col_var": "Value",
    "col_label": ["Value"],
    "boolean_value": false,
    "integer_value": false,
    "value": [0.20],
    "range": {
        "min": 0.0,
        "max": 1.0
    },
    "out_of_range_minmsg": "",
    "out_of_range_maxmsg": "",
    "out_of_range_action": "stop"
},
"_rate_TO_tax_other_disp": {
    "long_name": "Tax Rate  7",
    "description": "Turnover Tax ",
    "itr_ref": "Tax Law",
    "notes": "",
    "row_var": "Year",
    "row_label": [
        "2022"
    ],
    "start_year": 2022,
    "cpi_inflatable": false,
    "cpi_inflated": false,
    "col_var": "Value",
    "col_label": ["Value"],
    "boolean_value": false,
    "integer_value": false,
    "value": [0.05],
    "range": {
        "min": 0.0,
        "max": 1.0
    },
    "out_of_range_minmsg": "",
    "out_of_range_maxmsg": "",
    "out_of_range_action": "stop"
},
  "_rate_TO_tax_other": {
      "long_name": "Turnover Tax Rate applicable to turnover of taxpayers subjected to profit tax if TO exceeds threshold",
      "description": "Turnover Tax ",
      "itr_ref": "Tax Law",
      "notes": "",
      "row_var": "Year",
      "row_label": [
          "2022"
      ],
      "start_year": 2022,
      "cpi_inflatable": false,
      "cpi_inflated": false,
      "col_var": "Value",
      "col_label": ["Value"],
      "boolean_value": false,
      "integer_value": false,
      "value": [0.0],
      "range": {
          "min": 0.0,
          "max": 1.0
      },
      "out_of_range_minmsg": "",
      "out_of_range_maxmsg": "",
      "out_of_range_action": "stop"
  },
   "_TO_thold": {
       "long_name": "Turnover threshold (upper threshold)",
       "description": "If Turnover is below this threshold, taxpayer is subjected to turnover tax.",
       "itr_ref": "R code",
       "notes": "",
       "row_var": "AYEAR",
       "row_label": [
           "2022"
       ],
       "start_year": 2022,
       "cpi_inflatable": true,
       "cpi_inflated": false,
       "col_var": "",
       "col_label": [
       ],
       "boolean_value": false,
       "integer_value": false,
       "value": [
          115e+6
       ],
       "range": {
           "min": 0,
           "max": 9e+99
       },
       "out_of_range_minmsg": "",
       "out_of_range_maxmsg": "for _TO_thold2",
       "out_of_range_action": "stop"
   },
"_elasticity_cit_taxable_income_value": {
        "long_name": "Elasticity of Taxable Income",
        "description": "elasticity",
        "itr_ref": "elasticity",
        "notes": "",
        "row_var": "Year",
        "row_label": [
                "2022"
        ],
        "start_year": 2022,
        "cpi_inflatable": false,
        "cpi_inflated": false,
        "col_var": "Elasticity",
        "col_label": "",
        "boolean_value": false,
        "integer_value": false,
        "value": [      
                [0.0,
                0.0,
                0.0]
      ],
        "range": {
            "min": 0,
            "max": 1
        },
        "out_of_range_minmsg": "",
        "out_of_range_maxmsg": "",
        "out_of_range_action": "stop"
    },
"_elasticity_cit_taxable_income_threshold": {
        "long_name": "Elasticity of Taxable Income",
        "description": "elasticity",
        "itr_ref": "elasticity",
        "notes": "",
        "row_var": "Year",
        "row_label": [
                100000,
                1000000,
                9e99
        ],
        "start_year": 2022,
        "cpi_inflatable": false,
        "cpi_inflated": false,
        "col_var": "Elasticity",
        "col_label": "",
        "boolean_value": false,
        "integer_value": false,
        "value": [      
                [
                100000,
                1000000,
                9e99
                ]
      ],
        "range": {
            "min": 0,
            "max": 9e99
        },
        "out_of_range_minmsg": "",
        "out_of_range_maxmsg": "",
        "out_of_range_action": "stop"
    } 
}